mcdwld/__init__.py
mcdwld/mcdwld.py
mc_downloader-0.0.5.dist-info/LICENCE
mc_downloader-0.0.5.dist-info/METADATA
mc_downloader-0.0.5.dist-info/WHEEL
mc_downloader-0.0.5.dist-info/top_level.txt
mc_downloader-0.0.5.dist-info/RECORD
