Metadata-Version: 2.1
Name: mc-downloader
Version: 0.0.5
Summary: A downloader tool for Minecraft servers from Mojang services.
Home-page: https://github.com/Couapy/mc-downloader
Author: Couapy
Author-email: contact@marchand.cloud
License: MIT
Platform: UNKNOWN
Classifier: Programming Language :: Python :: 3
Classifier: License :: OSI Approved :: MIT License
Classifier: Operating System :: OS Independent
Requires-Python: >=3.6
Requires-Dist: certifi (>=2020.12.5)
Requires-Dist: chardet (>=4.0.0)
Requires-Dist: idna (>=2.10)
Requires-Dist: requests (>=2.25.1)
Requires-Dist: urllib3 (>=1.26.4)
